setup.py
src/fabistrano.py
src/fabistrano.egg-info/PKG-INFO
src/fabistrano.egg-info/SOURCES.txt
src/fabistrano.egg-info/dependency_links.txt
src/fabistrano.egg-info/requires.txt
src/fabistrano.egg-info/top_level.txt